CHANGES.txt
LICENSE.txt
MANIFEST.in
README.txt
bootstrap.py
buildout.cfg
setup.py
src/m01/__init__.py
src/m01.bayes.egg-info/PKG-INFO
src/m01.bayes.egg-info/SOURCES.txt
src/m01.bayes.egg-info/dependency_links.txt
src/m01.bayes.egg-info/namespace_packages.txt
src/m01.bayes.egg-info/not-zip-safe
src/m01.bayes.egg-info/requires.txt
src/m01.bayes.egg-info/top_level.txt
src/m01/bayes/README.txt
src/m01/bayes/__init__.py
src/m01/bayes/api.py
src/m01/bayes/bayes.py
src/m01/bayes/interfaces.py
src/m01/bayes/testing.py
src/m01/bayes/tests.py